[
  {
    "Day": 36,
    "Date": "Feb. 24",
    "Topic": "Sanctuary laws, Immigration, California",
    "Headline": "SF library begins campaign to support unauthorized immigrants",
    "Link": "http://www.sfchronicle.com/bayarea/article/SF-library-begins-campaign-to-support-10957847.php"
  },
  {
    "Day": 36,
    "Date": "Feb. 24",
    "Topic": "Democrats, Trump resistance, California",
    "Headline": "Feinstein answers questions; still gets hard time from protesters",
    "Link": "http://www.sfchronicle.com/politics/article/Feinstein-answers-questions-still-gets-hard-10957888.php"
  },
  {
    "Day": 36,
    "Date": "Feb. 24",
    "Topic": "Media, Trump Today",
    "Headline": "Trump Today: Some news outlets blocked from Trump 'gaggle'",
    "Link": "http://www.sfchronicle.com/news/article/Trump-Today-Some-news-outlets-blocked-from-White-10957603.php"
  },
  {
    "Day": 36,
    "Date": "Feb. 24",
    "Topic": "Trump soundoffs, Media, Trump Today",
    "Headline": "President slams FBI over leaked reports to media",
    "Link": "http://www.sfchronicle.com/news/article/Trump-Today-President-slams-FBI-over-leaked-10956702.php"
  },
  {
    "Day": 36,
    "Date": "Feb. 24",
    "Topic": "Trump resistance, California ",
    "Headline": "Seeds of a new resistance movement start to take hold",
    "Link": "http://www.sfchronicle.com/news/article/Seeds-of-a-new-resistance-movement-start-to-take-10955348.php"
  },
  {
    "Day": 35,
    "Date": "Feb. 23",
    "Topic": "California, Immigration, Sanctuary laws",
    "Headline": "Santa Cruz leaders slam feds over immigration detentions during gang operations",
    "Link": "http://www.sfchronicle.com/bayarea/article/Santa-Cruz-leaders-slam-feds-over-immigration-10955358.php"
  },
  {
    "Day": 35,
    "Date": "Feb. 23",
    "Topic": "California, Courts, Sanctuary laws",
    "Headline": "Santa Clara County calls Trump sanctuary order 'extortion'",
    "Link": "http://www.sfchronicle.com/bayarea/article/Santa-Clara-County-calls-Trump-s-sanctuary-10955184.php"
  },
  {
    "Day": 35,
    "Date": "Feb. 23",
    "Topic": "California, Republicans",
    "Headline": "California GOP dilemma: Do we embrace Trump or not?",
    "Link": "http://www.sfchronicle.com/politics/article/California-GOP-dilemma-Do-we-embrace-Trump-or-10955337.php"
  },
  {
    "Day": 35,
    "Date": "Feb. 23",
    "Topic": "California, Environment, Democrats",
    "Headline": "Fearing Trump, California lawmakers move to safeguard environmental rules",
    "Link": "http://www.sfchronicle.com/politics/article/California-bills-would-keep-current-environmental-10955444.php"
  },
  {
    "Day": 35,
    "Date": "Feb. 23",
    "Topic": "California, Marijuana",
    "Headline": "California, Trump could clash over legal pot",
    "Link": "http://www.sfchronicle.com/business/article/Trump-admin-indicates-greater-enforcement-10955341.php"
  },
  {
    "Day": 34,
    "Date": "Feb. 22",
    "Topic": "California, Immigration, Education",
    "Headline": "Court won't let aid be taken from immigrant UC students",
    "Link": "http://www.sfchronicle.com/news/article/Court-won-t-let-aid-to-be-taken-from-immigrant-10952578.php"
  },
  {
    "Day": 34,
    "Date": "Feb. 22",
    "Topic": "California, Immigration, Sanctuary laws",
    "Headline": "SF has bold proposal to protect Muslims",
    "Link": "http://www.sfchronicle.com/politics/article/SF-has-bold-proposal-to-protect-Muslims-10952506.php"
  },
  {
    "Day": 34,
    "Date": "Feb. 22",
    "Topic": "LGBT, California, Cabinet",
    "Headline": "Conservative applause, activist anger over Trump's transgender rollback",
    "Link": "http://www.sfchronicle.com/news/article/Conservative-applause-activist-anger-over-10952705.php"
  },
  {
    "Day": 34,
    "Date": "Feb. 22",
    "Topic": "LGBT, Cabinet, Trump Today",
    "Headline": "Obama policy on transgender school bathrooms repealed",
    "Link": "http://www.sfchronicle.com/nation/article/Trump-Today-Obama-policy-on-transgender-school-10952484.php"
  },
  {
    "Day": 34,
    "Date": "Feb. 22",
    "Topic": "Congress, California, Transportation",
    "Headline": "California’s top Republican ignored business plea to help Caltrain",
    "Link": "http://www.sfchronicle.com/bayarea/article/California-s-top-Republican-ignored-business-10949198.php"
  },
  {
    "Day": 33,
    "Date": "Feb. 21",
    "Topic": "Congress, California, Health care",
    "Headline": "State fears Trump will topple health care gains under Obamacare",
    "Link": "http://www.sfchronicle.com/business/article/California-fears-Trump-will-overturn-health-gains-10944890.php"
  },
  {
    "Day": 33,
    "Date": "Feb. 21",
    "Topic": "Trump resistance, Congress, Health care",
    "Headline": "GOP Rep. McClintock gets an earful at Northern California town hall",
    "Link": "http://www.sfchronicle.com/politics/article/GOP-Rep-McClintock-gets-an-earful-at-Northern-10949828.php"
  },
  {
    "Day": 33,
    "Date": "Feb. 21",
    "Topic": "Trump soundoffs, Trump resistance, Anti-Semitism, Trump Today",
    "Headline": "Anne Frank Center says Trump 'too lttle, too late'",
    "Link": "http://www.sfchronicle.com/nation/article/Trump-Today-Anne-Frank-Center-says-Trump-too-10948873.php"
  },
  {
    "Day": 33,
    "Date": "Feb. 21",
    "Topic": "Immigration, Executive order, Trump Today",
    "Headline": "Beefed-up Border Patrol, more lockups for undocumented immigrants",
    "Link": "http://www.sfchronicle.com/bayarea/article/Trump-Today-Beefed-up-Border-Patrol-more-10948471.php"
  },
  {
    "Day": 33,
    "Date": "Feb. 21",
    "Topic": "Immigration, Executive order",
    "Headline": "Trump's new priorities expose more immigrants to deportation",
    "Link": "http://www.sfchronicle.com/bayarea/article/Trump-s-new-priorities-expose-more-immigrants-10949458.php"
  },
  {
    "Day": 33,
    "Date": "Feb. 21",
    "Topic": "California, Health care",
    "Headline": "State fears Trump will topple health care gains under Obamacare",
    "Link": "http://www.sfchronicle.com/business/article/California-fears-Trump-will-overturn-health-gains-10944890.php"
  },
  {
    "Day": 32,
    "Date": "Feb. 20",
    "Topic": "Cabinet, Security",
    "Headline": "Army Lt. Gen. H.R. McMaster is named President Donald Trump's national security adviser",
    "Link": "http://www.sfchronicle.com/news/article/Army-Lt-Gen-H-R-McMaster-is-named-President-10945964.php"
  },
  {
    "Day": 31,
    "Date": "Feb. 19",
    "Topic": "Trump resistance, Democrats, Congress",
    "Headline": "Taking on Trump puts Kamala Harris in the spotlight",
    "Link": "http://www.sfchronicle.com/bayarea/matier-ross/article/Taking-on-Trump-puts-Kamala-Harris-in-spotlight-10942291.php"
  },
  {
    "Day": 31,
    "Date": "Feb. 19",
    "Topic": "Trump soundoffs, Sweden, Terrorism",
    "Headline": "Trump says remark about Sweden referred to something on TV",
    "Link": "http://www.sfchronicle.com/news/politics/article/Swedes-scratch-heads-at-Trump-s-suggestion-of-10943844.php"
  },
  {
    "Day": 30,
    "Date": "Feb. 18",
    "Topic": "Russia, Congress, Trump soundoffs",
    "Headline": "Good news now for Trump, but bad news may be just around the bend",
    "Link": "http://www.sfchronicle.com/bayarea/williesworld/article/Good-news-now-for-Trump-but-bad-news-may-be-just-10942341.php"
  },
  {
    "Day": 30,
    "Date": "Feb. 18",
    "Topic": "Trump soundoffs, Courts, Congress",
    "Headline": "Trump attack may reopen debate on splitting Ninth Circuit in SF",
    "Link": "http://www.sfchronicle.com/nation/article/Trump-attack-may-reopen-debate-on-splitting-Ninth-10943304.php"
  },
  {
    "Day": 30,
    "Date": "Feb. 18",
    "Topic": "Trump resistance, Cabinet, Congress",
    "Headline": "Washington's coup fever heats up",
    "Link": "http://www.sfchronicle.com/news/article/Washington-s-coup-fever-heats-up-10942988.php"
  },
  {
    "Day": 30,
    "Date": "Feb. 18",
    "Topic": "Trump resistance, California, Trump soundoffs",
    "Headline": "Trump's gap between talk, action could benefit California",
    "Link": "http://www.sfchronicle.com/politics/article/Trump-s-gap-between-talk-action-could-benefit-10943321.php"
  },
  {
    "Day": 29,
    "Date": "Feb. 17",
    "Topic": "Trump resistance, Congress, Democrats",
    "Headline": "Trump's storm keeps Democrats busy on many fronts",
    "Link": "http://www.sfchronicle.com/politics/article/Trump-s-storm-keeps-Democrats-busy-on-many-10941912.php"
  },
  {
    "Day": 29,
    "Date": "Feb. 17",
    "Topic": "California, Congress, Republicans",
    "Headline": "Trump administration deals a big setback to California",
    "Link": "http://www.sfchronicle.com/bayarea/matier-ross/article/Trump-administration-deals-a-big-setback-to-10941880.php"
  },
  {
    "Day": 29,
    "Date": "Feb. 17",
    "Topic": "Cabinet, Trump Today",
    "Headline": "Retired Lt. Gen. Kellogg 1 of 4 candidates for NSA",
    "Link": "http://www.sfchronicle.com/nation/article/Trump-Today-Retired-Lt-Gen-Kellogg-1-of-4-10941038.php"
  },
  {
    "Day": 29,
    "Date": "Feb. 17",
    "Topic": "Cabinet, Marijuana",
    "Headline": "Trump may allow states some leeway with marijuana",
    "Link": "http://www.sfchronicle.com/news/article/Trump-may-allow-states-some-leeway-with-marijuana-10941928.php"
  },
  {
    "Day": 29,
    "Date": "Feb. 17",
    "Topic": "Immigration, Executive order, Trump Today",
    "Headline": "Report that Guard could be used to round up immigrants is 'false'",
    "Link": "http://www.sfchronicle.com/nation/article/Trump-Today-Report-that-Guard-could-be-used-to-10940498.php"
  },
  {
    "Day": 29,
    "Date": "Feb. 17",
    "Topic": "Cabinet, Trump Today, Environment",
    "Headline": "Senate confirms Pruitt for EPA over environmentalists’ opposition",
    "Link": "http://www.sfchronicle.com/politics/article/Senate-confirms-Pruitt-for-EPA-over-10940782.php"
  },
  {
    "Day": 28,
    "Date": "Feb. 16",
    "Topic": "Trump soundoffs, Trump supporters, Media, Russia",
    "Headline": "Trump's base unfazed by recent allegations, criticisms",
    "Link": "http://www.sfchronicle.com/politics/article/Trump-s-base-unfazed-by-recent-allegations-10939579.php"
  },
  {
    "Day": 28,
    "Date": "Feb. 16",
    "Topic": "Cabinet, Trump Today",
    "Headline": "Trump today: Alexander Acosta, Florida dean, nominated for Labor",
    "Link": "http://www.sfchronicle.com/business/article/Trump-today-Alexander-Acosta-Florida-dean-10937774.php"
  },
  {
    "Day": 28,
    "Date": "Feb. 16",
    "Topic": "Immigration, Travel ban, Courts, Executive order",
    "Headline": "Administration's plans new travel ban to meet courts' objections",
    "Link": "http://www.sfchronicle.com/nation/article/Trump-Today-President-s-PAC-emails-media-10938925.php"
  },
  {
    "Day": 28,
    "Date": "Feb. 16",
    "Topic": "Media, Trump supporters, Trump Today",
    "Headline": "President's PAC emails 'media accountability survey'",
    "Link": "http://www.sfchronicle.com/nation/article/Trump-Today-President-s-PAC-emails-media-10938925.php"
  },
  {
    "Day": 28,
    "Date": "Feb. 16",
    "Topic": "Tech, Immigration",
    "Headline": "Trump could scapegoat H-1B visas for immigration goals",
    "Link": "http://www.sfchronicle.com/business/article/Trump-could-scapegoat-H-1B-visas-for-immigration-10938999.php"
  },
  {
    "Day": 27,
    "Date": "Feb. 15",
    "Topic": "Trump resistance, Entertainment",
    "Headline": "Voters who show up have way more political power than Beyoncé",
    "Link": "http://www.sfchronicle.com/politics/article/Voters-who-show-up-have-way-more-political-power-10935734.php"
  },
  {
    "Day": 27,
    "Date": "Feb. 15",
    "Key Event?": "Yes",
    "Topic": "Cabinet",
    "Headline": "Puzder withdraws nomination to be Trump's labor secretary",
    "Link": "http://www.sfchronicle.com/news/politics/article/Puzder-s-nomination-as-Labor-secretary-in-serious-10935076.php"
  },
  {
    "Day": 27,
    "Date": "Feb. 15",
    "Topic": "Trump soundoffs, Media, Russia, Cabinet, Trump Today",
    "Headline": "President says Russian phone call leaks 'un-American'",
    "Link": "http://www.sfchronicle.com/politics/article/Trump-Today-President-says-Russian-phone-call-10934927.php"
  },
  {
    "Day": 26,
    "Date": "Feb. 14",
    "Topic": "Health care, Taxes",
    "Headline": "Quiet IRS change could undermine Obamacare, supporters say",
    "Link": "http://www.sfchronicle.com/business/networth/article/Quiet-IRS-change-could-undermine-Obamacare-10932798.php"
  },
  {
    "Day": 26,
    "Date": "Feb. 14",
    "Topic": "Immigration, Courts, Trump soundoffs",
    "Headline": "Judge, in effect tells Trump administration: See you in court",
    "Link": "http://www.sfchronicle.com/nation/article/Judge-in-effect-tells-Trump-administration-See-10932853.php"
  },
  {
    "Day": 26,
    "Date": "Feb. 14",
    "Topic": "California",
    "Headline": "Trump approves California's request for emergency aid",
    "Link": "http://www.sfchronicle.com/news/article/Trump-approves-California-s-request-for-10932968.php"
  },
  {
    "Day": 26,
    "Date": "Feb. 14",
    "Key Event?": "Yes",
    "Topic": "Russia, Trump supporters",
    "Headline": "Trump team, Russian agents reportedly in contact during campaign",
    "Link": "http://www.sfchronicle.com/world/article/Trump-team-Russian-spies-reportedly-in-contact-10933175.php"
  },
  {
    "Day": 26,
    "Date": "Feb. 14",
    "Topic": "Business, Trump resistance",
    "Headline": "Boycotting companies tied to president new weapon in US politics",
    "Link": "http://www.sfchronicle.com/politics/article/Boycotting-companies-tied-to-president-new-weapon-10932900.php"
  },
  {
    "Day": 26,
    "Date": "Feb. 14",
    "Topic": "Business, Energy, Trump Today",
    "Headline": "Another win for big oil",
    "Link": "http://www.sfchronicle.com/business/article/Trump-Today-Another-big-win-for-oil-10932330.php"
  },
  {
    "Day": 26,
    "Date": "Feb. 14",
    "Topic": "California, Trump Today",
    "Headline": "White House 'keeping close eye' on Oroville crisis",
    "Link": "http://www.sfchronicle.com/news/article/Trump-Today-White-House-keeping-close-eye-10931865.php"
  },
  {
    "Day": 26,
    "Date": "Feb. 14",
    "Topic": "Cabinet, Russia, Trump soundoffs, Trump Today",
    "Headline": "President says Flynn resigning 'not the real story'",
    "Link": "http://www.sfchronicle.com/news/article/Trump-Today-President-says-Flynn-resigning-not-10931284.php"
  },
  {
    "Day": 25,
    "Date": "Feb. 13",
    "Topic": "California",
    "Headline": "California waits to hear from Trump on disaster aid request",
    "Link": "http://www.sfchronicle.com/news/article/California-waits-to-hear-from-Trump-on-disaster-10929944.php"
  },
  {
    "Day": 25,
    "Date": "Feb. 13",
    "Topic": "Trump resistance, Fashion",
    "Headline": "Trump protests trending at New York Fashion Week",
    "Link": "http://www.sfchronicle.com/nation/article/Trump-protests-trending-at-New-York-Fashion-Week-10930301.php"
  },
  {
    "Day": 25,
    "Date": "Feb. 13",
    "Key Event?": "Yes",
    "Topic": "Cabinet, Russia",
    "Headline": "National Security Adviser Michael Flynn resigns",
    "Link": "http://www.sfchronicle.com/news/politics/article/Embattled-national-security-adviser-s-fate-10927961.php"
  },
  {
    "Day": 24,
    "Date": "Feb. 12",
    "Topic": "Trump resistance, Entertainment",
    "Headline": "Grammys strike a political note amid flawed ceremony",
    "Link": "http://www.sfchronicle.com/music/article/Grammys-strike-a-political-note-amid-flawed-10927820.php"
  },
  {
    "Day": 23,
    "Date": "Feb. 11",
    "Topic": "Women, abortion, Trump supporters, Trump resistance",
    "Headline": "Protests at Planned Parenthood clinics met with opposition",
    "Link": "http://www.sfchronicle.com/bayarea/article/Protests-at-Planned-Parenthood-clinics-met-with-10925933.php"
  },
  {
    "Day": 23,
    "Date": "Feb. 11",
    "Topic": "Women, Trump resistance",
    "Headline": "A day without women: 'General strike' against Trump gains traction",
    "Link": "http://www.sfchronicle.com/bayarea/article/A-day-without-women-General-strike-against-10925808.php"
  },
  {
    "Day": 23,
    "Date": "Feb. 11",
    "Topic": "Tech, Trump resistance, Business",
    "Headline": "Tech firms find their voice in resisting Trump, for now",
    "Link": "http://www.sfchronicle.com/politics/article/Techies-find-their-voice-in-anti-Trump-10926105.php"
  },
  {
    "Day": 22,
    "Date": "Feb. 10",
    "Topic": "Immigration, Courts",
    "Headline": "Advocates for people facing deportation have limited ways to help",
    "Link": "http://www.sfchronicle.com/bayarea/article/Advocates-for-people-facing-deportation-have-10925148.php"
  },
  {
    "Day": 22,
    "Date": "Feb. 10",
    "Topic": "Courts, Immigration",
    "Headline": "Trump's claim aside, travel ruling based in law, scholars say",
    "Link": "http://www.sfchronicle.com/nation/article/Trump-s-claim-aside-3-0-ruling-on-travel-ban-10924698.php"
  },
  {
    "Day": 22,
    "Date": "Feb. 10",
    "Topic": "Tech, Immigration, Business",
    "Headline": "Unease over immigration hurting tech recruiting",
    "Link": "http://www.sfchronicle.com/business/article/Unease-over-immigration-hurting-tech-recruiting-10924210.php"
  },
  {
    "Day": 21,
    "Date": "Feb. 9",
    "Key Event?": "Yes",
    "ContentType": "article",
    "Topic": "Courts, Immigration",
    "NewsEvent": "Appeals court rules on travel ban",
    "Headline": "Court refuses to lift stay on Trump's travel ban",
    "Link": "http://www.sfchronicle.com/news/article/Court-refuses-to-lift-stay-on-Trump-s-travel-ban-10921770.php"
  },
  {
    "Day": 21,
    "Date": "Feb. 9",
    "Topic": "California, Polls",
    "Headline": "Brutal numbers for Trump, high marks for Brown in new state poll",
    "Link": "http://www.sfchronicle.com/politics/article/Brutal-numbers-for-Trump-high-marks-for-Brown-in-10921820.php"
  },
  {
    "Day": 21,
    "Date": "Feb. 9",
    "ContentType": "trump today",
    "Topic": "Trump Today, Trump family",
    "NewsEvent": "Trump adviser pushes Ivanka clothing line",
    "Headline": "Kellyanne Conway tells people to \"go buy Ivanka's stuff'",
    "Link": "http://www.sfchronicle.com/nation/article/Trump-today-Kellyanne-Conway-tells-people-to-10920367.php"
  },
  {
    "Day": 21,
    "Date": "Feb. 9",
    "ContentType": "column",
    "Topic": "Trump resistance",
    "NewsEvent": "Trump opponents try to cope",
    "Headline": "Wise advice from Berkeley scholar: Don't have a cow, America",
    "Link": "http://www.sfchronicle.com/news/article/Wise-advice-from-Berkeley-scholar-Don-t-have-a-10918787.php"
  },
  {
    "Day": 21,
    "Date": "Feb. 9",
    "Topic": "Trump Today, Executive order, Crime",
    "Headline": "Trump Today: President signs executive orders on crime and safety",
    "Link": "http://www.sfchronicle.com/politics/article/Trump-Today-President-signs-executive-orders-on-10921066.php"
  },
  {
    "Day": 21,
    "Date": "Feb. 9",
    "Topic": "Tech, Business",
    "Headline": "Trump’s populist revolt could put the brakes on self-driving cars",
    "Link": "http://www.sfchronicle.com/business/article/Trump-s-populist-revolt-could-put-the-brakes-on-10922029.php"
  },
  {
    "Day": 20,
    "Date": "Feb. 8",
    "ContentType": "article",
    "Topic": "Trump soundoffs, Trump family",
    "NewsEvent": "Ethics experts look at Trump promoting family business",
    "Headline": "Is Trump using the Oval Office to try to enrich his family?",
    "Link": "http://www.sfchronicle.com/politics/article/Is-Trump-using-the-Oval-Office-to-try-to-enrich-10919106.php"
  },
  {
    "Day": 20,
    "Date": "Feb. 8",
    "ContentType": "article",
    "Topic": "Trump resistance, Congress, Republicans",
    "NewsEvent": "Jesse Jackson criticizes silencing of Elizabeth Warren",
    "Headline": "Jesse Jackson slams Senate Republicans for hushing Sen. Warren",
    "Link": "http://www.sfchronicle.com/news/article/Jesse-Jackson-slams-Senate-Republicans-for-10918778.php"
  },
  {
    "Day": 20,
    "Date": "Feb. 8",
    "ContentType": "article",
    "Topic": "Cabinet, Congress",
    "NewsEvent": "Elizabeth Warren silenced in Senate",
    "Headline": "Senate newcomer Harris leaps into fray over silencing of Warren",
    "Link": "http://www.sfchronicle.com/nation/article/Senate-newcomer-Harris-leaps-into-fray-over-10918992.php"
  },
  {
    "Day": 20,
    "Date": "Feb. 8",
    "ContentType": "article",
    "Topic": "Courts, Trump soundoffs, Immigration, Congress",
    "NewsEvent": "Conservatives target Ninth Circuit appeals court",
    "Headline": "SF-based appeals court back on conservatives' radar as Trump ruling nears",
    "Link": "http://www.sfchronicle.com/bayarea/article/SF-based-court-back-in-conservatives-sights-as-10918844.php"
  },
  {
    "Day": 20,
    "Date": "Feb. 8",
    "ContentType": "trump today",
    "Topic": "Trump Today, Immigration, Courts, Executive order, Trump soundoffs",
    "NewsEvent": "Trump pressures appeals court",
    "Headline": "President sounds off on 9th Circuit Court judges",
    "Link": "http://www.sfchronicle.com/news/article/Trump-update-President-blasts-9th-Circuit-Court-10917302.php"
  },
  {
    "Day": 20,
    "Date": "Feb. 8",
    "ContentType": "trump today",
    "Topic": "Trump Today, Trump soundoffs, Business",
    "NewsEvent": "Trump pushes daughter's business",
    "Headline": "President tweets Nordstrom treated Ivanka 'unfairly'",
    "Link": "http://www.sfchronicle.com/news/article/Trump-Today-President-tweets-Nordstrom-treated-10917900.php"
  },
  {
    "Day": 20,
    "Date": "Feb. 8",
    "ContentType": "trump today",
    "Topic": "Trump Today, Supreme Court, Trump soundoffs",
    "NewsEvent": "Gorsuch reacts to Trump on judiciary",
    "Headline": "Gorsuch calls Trump tweets 'demoralizing'",
    "Link": "http://www.sfchronicle.com/news/article/Trump-Today-Gorsuch-calls-Trump-tweets-10918701.php"
  },
  {
    "Day": 20,
    "Date": "Feb. 8",
    "ContentType": "trump today",
    "Topic": "Trump Today, Immigration, Executive order, Courts",
    "NewsEvent": "Court ruling pending",
    "Headline": "Court says no ruling Wednesday on travel ban",
    "Link": "http://www.sfchronicle.com/nation/article/Trump-Today-Court-says-no-ruling-Wednesday-on-10918229.php"
  },
  {
    "Day": 19,
    "Date": "Feb. 8",
    "Topic": "Trump Today, Tech, Business",
    "Headline": "Trump Today: Intel CEO announces $7 billion factory plan",
    "Link": "http://www.sfchronicle.com/business/article/Trump-Today-Intel-CEO-announces-7-billion-10918032.php"
  },
  {
    "Day": 19,
    "Date": "Feb. 7",
    "Key Event?": "Yes",
    "ContentType": "article",
    "Topic": "Immigration, Executive order, Courts",
    "NewsEvent": "Appeals court hears Trump ban",
    "Headline": "Court hints at keeping Trump order on hold",
    "Link": "http://www.sfchronicle.com/nation/article/Court-hints-at-keeping-Trump-order-on-hold-10915838.php"
  },
  {
    "Day": 18,
    "Date": "Feb. 6",
    "ContentType": "article",
    "Topic": "Foreign relations, Foreign policy, Protests",
    "NewsEvent": "Trump's management style assessed",
    "Headline": "Will Trump's 'Art of the Deal' bravado translate to politics?",
    "Link": "http://www.sfchronicle.com/politics/article/Will-Trump-s-Art-of-the-Deal-bravado-10912854.php?t=b7551817d9&cmpid=twitter-premium"
  },
  {
    "Day": 18,
    "Date": "Feb. 6",
    "ContentType": "column",
    "Topic": "Transportation, Congress, Republicans",
    "NewsEvent": "Republicans target Caltrain, high-speed rail",
    "Headline": "With Trump in charge, Republicans target Caltrain",
    "Link": "http://www.sfchronicle.com/bayarea/matier-ross/article/With-Trump-in-charge-Republicans-target-Caltrain-10907794.php"
  },
  {
    "Day": 18,
    "Date": "Feb. 6",
    "ContentType": "article",
    "Topic": "Immigration, Executive order, Courts",
    "NewsEvent": "Appeals court to hear Trump ban",
    "Headline": "Trump's travel ban to be argued Tuesday in S.F. federal court",
    "Link": "http://www.sfchronicle.com/nation/article/Trump-s-travel-ban-to-be-argued-Tuesday-in-S-F-10912699.php"
  },
  {
    "Day": 17,
    "Date": "Feb. 5",
    "Key Event?": "Yes",
    "Topic": "Immigration, Executive order, Tech",
    "Headline": "Tech puts up (mostly) united front against Trump travel ban",
    "Link": "http://www.sfchronicle.com/business/article/Apple-Facebook-Google-Microsoft-file-brief-10910677.php"
  },
  {
    "Day": 17,
    "Date": "Feb. 5",
    "ContentType": "article",
    "Topic": "Trump supporters",
    "NewsEvent": "Trump backers look at his first two weeks",
    "Headline": "Trump's stormy start doesn't rattle San Joaquin Valley",
    "Link": "http://www.sfchronicle.com/news/article/Trump-s-stormy-start-doesn-t-rattle-San-10908973.php"
  },
  {
    "Day": 17,
    "Date": "Feb. 5",
    "ContentType": "article",
    "Topic": "Immigration, Executive order, Courts",
    "NewsEvent": "Immigrants start landing in U.S.",
    "Headline": "Yemeni girl's travel ordeal ends with U.S. citizenship",
    "Link": "http://www.sfchronicle.com/bayarea/article/Tearful-reunion-at-SFO-for-immigrant-family-10910347.php"
  },
  {
    "Day": 16,
    "Date": "Feb. 4",
    "ContentType": "article",
    "Topic": "Immigration, Executive order, Courts",
    "NewsEvent": "Immigrant families react to court order",
    "Headline": "Immigrant families hopeful after decision halting Trump order",
    "Link": "http://www.sfchronicle.com/bayarea/article/Immigrant-families-hopeful-after-judge-s-10908519.php"
  },
  {
    "Day": 15,
    "Date": "Feb. 3",
    "Key Event?": "Yes",
    "ContentType": "article",
    "Topic": "Immigration, Executive order, Courts",
    "NewsEvent": "Judge halts immigration ban",
    "Headline": "Federal judge halts Trump immigration order nationwide",
    "Link": "http://www.sfchronicle.com/nation/article/Federal-judge-halts-Trump-immigration-order-10907721.php"
  },
  {
    "Day": 15,
    "Date": "Feb. 3",
    "ContentType": "article",
    "Topic": "Deregulation, Supreme Court",
    "NewsEvent": "Supreme Court, Neil Gorsuch",
    "Headline": "High court nominee Gorsuch likely Trump ally in regulation cuts",
    "Link": "http://www.sfchronicle.com/nation/article/High-court-nominee-Gorsuch-likely-Trump-ally-in-10907474.php"
  },
  {
    "Day": 15,
    "Date": "Feb. 3",
    "ContentType": "trump today",
    "Topic": "Trump Today, Lawsuit, Immigration",
    "NewsEvent": "Lawsuits over travel ban",
    "Headline": "2 Bay Area college students sue over travel ban",
    "Link": "http://www.sfchronicle.com/bayarea/article/Trump-update-2-Bay-Area-college-students-sue-10907178.php"
  },
  {
    "Day": 15,
    "Date": "Feb. 3",
    "ContentType": "trump today",
    "Topic": "Trump Today, Tech, Immigration",
    "NewsEvent": "Tech leaders on travel ban",
    "Headline": "Tech giants join forces in letter against travel ban",
    "Link": "http://www.sfchronicle.com/bayarea/article/Trump-update-Tech-giants-join-forces-in-letter-10906212.php"
  },
  {
    "Day": 15,
    "Date": "Feb. 3",
    "ContentType": "trump today",
    "Topic": "Trump Today, Executive order, finance",
    "NewsEvent": "Tech leaders on travel ban",
    "Headline": "Trump update: Trump starts rollback of Dodd-Frank rules",
    "Link": "http://www.sfchronicle.com/business/article/Trump-kicks-off-rollback-of-Dodd-Frank-financial-10906491.php"
  },
  {
    "Day": 15,
    "Date": "Feb. 3",
    "Topic": "Environment, Business, Tech",
    "Headline": "Trump’s push to dump regulations divides Silicon Valley",
    "Link": "http://www.sfchronicle.com/business/article/Trump-s-push-to-dump-regulations-divides-10905113.php"
  },
  {
    "Day": 15,
    "Date": "Feb. 3",
    "Topic": "Business, Executive order",
    "Headline": "Trump’s fiduciary rule order could pose problem for investors",
    "Link": "http://www.sfchronicle.com/business/article/Trump-s-fiduciary-rule-order-could-pose-problem-10907519.php"
  },
  {
    "Day": 14,
    "Date": "Feb. 2",
    "Topic": "Tech, Immigration",
    "Headline": "Trump order dashes hopes of would-be entrepreneurs",
    "Link": "http://www.sfchronicle.com/business/article/Trump-order-dashes-hopes-of-would-be-entrepreneurs-10901727.php"
  },
  {
    "Day": 14,
    "Date": "Feb. 2",
    "ContentType": "trump today",
    "Topic": "Trump Today, Deregulation, Education",
    "NewsEvent": "Education deregulation",
    "Headline": "Falwell selected for education deregulation task force",
    "Link": "http://www.sfchronicle.com/news/article/Trump-update-Falwell-selected-for-education-10905095.php"
  },
  {
    "Day": 14,
    "Date": "Feb. 2",
    "ContentType": "article",
    "Topic": "Protests, Funding",
    "NewsEvent": "Trump criticizes opponents",
    "Headline": "Trump's threat to cut off federal funds after fiery protest stuns UC",
    "Link": "http://www.sfchronicle.com/politics/article/Trump-s-threat-to-cut-federal-funds-after-fiery-10904717.php"
  },
  {
    "Day": 14,
    "Date": "Feb. 2",
    "ContentType": "trump today",
    "Topic": "Trump Today, Security, Democrats",
    "NewsEvent": "Democratic resistance, National Security Council",
    "Headline": "Rep. Lee wants Bannon booted from the NSC",
    "Link": "http://www.sfchronicle.com/nation/article/Trump-update-Rep-Lee-wants-Bannon-booted-from-10904164.php"
  },
  {
    "Day": 14,
    "Date": "Feb. 2",
    "ContentType": "trump today",
    "Topic": "Trump Today, Trump resistance",
    "NewsEvent": "Trump criticizes opponents",
    "Headline": "President trashes Schwarzenegger's TV ratings",
    "Link": "http://www.sfchronicle.com/bayarea/article/Trump-update-President-trashes-10903380.php"
  },
  {
    "Day": 14,
    "Date": "Feb. 2",
    "ContentType": "trump today",
    "Topic": "Trump Today, Protests, Funding, Trump soundoffs",
    "NewsEvent": "Protests, Trump on Twitter",
    "Headline": "Protest at UC Berkeley prompts funding threat",
    "Link": "http://www.sfchronicle.com/bayarea/article/Trump-update-Protest-at-UC-Berkeley-prompts-10902945.php"
  },
  {
    "Day": 14,
    "Date": "Feb. 2",
    "ContentType": "trump today",
    "Topic": "Trump Today, Tech",
    "NewsEvent": "Silicon Valley and Trump",
    "Headline": "Peter Thiel confidant appointed to NSC staff",
    "Link": "http://www.sfchronicle.com/business/article/Trump-update-Peter-Thiel-confidant-appointed-to-10903818.php"
  },
  {
    "Day": 14,
    "Date": "Feb. 2",
    "Key Event?": "Yes",
    "ContentType": "trump today",
    "Topic": "Trump Today, Tech",
    "NewsEvent": "Silicon Valley and Trump",
    "Headline": "Uber CEO quits Trump advisory council",
    "Link": "http://www.sfchronicle.com/business/article/Uber-CEO-quits-Trump-advisory-council-10904172.php"
  },
  {
    "Day": 13,
    "Date": "Feb. 1",
    "ContentType": "article",
    "Topic": "Democrats, Protests, Supreme Court",
    "NewsEvent": "Democrats' resistance to Trump picks",
    "Headline": "The resistance urges Democrats to oppose everything Trump wants",
    "Link": "http://www.sfchronicle.com/politics/article/The-resistance-urges-Democrats-to-oppose-10901980.php"
  },
  {
    "Day": 13,
    "Date": "Feb. 1",
    "ContentType": "article",
    "Topic": "Supreme Court, Democrats",
    "NewsEvent": "Supreme Court pick, Neil Gorsuch, Democratic opposition",
    "Headline": "Feinstein signals she'll lead Democrats against Gorsuch",
    "Link": "http://www.sfchronicle.com/nation/article/Feinstein-signals-she-ll-lead-Democrats-against-10901762.php"
  },
  {
    "Day": 13,
    "Date": "Feb. 1",
    "ContentType": "column",
    "Topic": "Trade, Economy",
    "NewsEvent": "Trump's executive orders on the economy",
    "Headline": "Trump policies may harm economy",
    "Link": "http://www.sfchronicle.com/business/article/Divisive-policies-will-harm-Trump-s-plans-to-10901387.php"
  },
  {
    "Day": 13,
    "Date": "Feb. 1",
    "ContentType": "trump today",
    "Topic": "Trump Today, Executive order, Health care, California",
    "NewsEvent": "California resistance to Trump ",
    "Headline": "California lawmakers to confer with Planned Parenthood ",
    "Link": "http://www.sfchronicle.com/news/article/Calif-resistance-Lawmakers-to-confer-with-10901616.php"
  },
  {
    "Day": 13,
    "Date": "Feb. 1",
    "ContentType": "column",
    "Topic": "Travel ban, Immigration, Executive order",
    "NewsEvent": "Immigration restrictions",
    "Headline": "East Bay Muslims make gestures of good faith in time of crisis",
    "Link": "http://www.sfchronicle.com/news/article/East-Bay-Muslims-make-gestures-of-good-faith-in-10898323.php"
  },
  {
    "Day": 13,
    "Date": "Feb. 1",
    "ContentType": "trump today",
    "Topic": "Trump Today, Travel ban, Executive order",
    "NewsEvent": "Immigration restrictions",
    "Headline": "Travel ban? It depends on the meaning of 'ban'",
    "Link": "http://www.sfchronicle.com/business/article/Trump-update-Travel-ban-Depends-on-what-the-10900483.php"
  },
  {
    "Day": 13,
    "Date": "Feb. 1",
    "ContentType": "trump today",
    "Topic": "Trump Today, Race relations",
    "NewsEvent": "Black History Month speech",
    "Headline": "Trump praises 'amazing job' by Frederick Douglass",
    "Link": "http://www.sfchronicle.com/bayarea/article/Trump-update-He-praises-amazing-job-by-10900531.php",
    "Visual": "http://ww4.hdnux.com/photos/56/71/01/12292179/3/920x920.jpg"
  },
  {
    "Day": 13,
    "Date": "Feb. 1",
    "ContentType": "trump today",
    "Topic": "Trump Today, Cabinet",
    "NewsEvent": "Secretary of state nomination",
    "Headline": "Trump update: California senators vote against Rex Tillerson nomination",
    "Link": "http://www.sfchronicle.com/business/article/Trump-update-Senate-confirms-Rex-Tillerson-as-10900949.php",
    "Visual": "http://ww2.hdnux.com/photos/56/71/24/12293413/5/920x920.jpg"
  },
  {
    "Day": 13,
    "Date": "Feb. 1",
    "ContentType": "trump today",
    "Topic": "Trump Today",
    "NewsEvent": "Firing of acting attorney general ",
    "Headline": "Speier nominates fired Yates for courage award",
    "Link": "http://www.sfchronicle.com/news/article/Trump-update-Speier-nominates-fired-Yates-for-10900033.php",
    "Visual": "http://ww1.hdnux.com/photos/56/70/64/12291336/9/920x1240.jpg"
  },
  {
    "Day": 12,
    "Date": "Jan. 31",
    "ContentType": "article",
    "Topic": "Tech",
    "NewsEvent": "Protests over immigration restrictions",
    "Headline": "Travel ban puts Uber and Lyft in spotlight",
    "Link": "http://www.sfchronicle.com/business/article/Uber-Lyft-in-spotlight-as-travel-ban-roils-10895252.php"
  },
  {
    "Day": 12,
    "Date": "Jan. 31",
    "ContentType": "trump today",
    "Topic": "Trump Today, Environment",
    "NewsEvent": "Letter on climate change to Trump",
    "Headline": "UC, CSU faculty send president warning on climate change",
    "Link": "http://www.sfchronicle.com/news/article/Trump-update-UC-faculty-sends-president-warning-10898068.php"
  },
  {
    "Day": 12,
    "Date": "Jan. 31",
    "ContentType": "trump today",
    "Topic": "Trump Today, Supreme Court",
    "NewsEvent": "Supreme Court pick, Neil Gorsuch",
    "Headline": "Feinstein, Harris unleash tweet storms against Gorsuch",
    "Link": "http://www.sfchronicle.com/news/article/Trump-update-Feinstein-Harris-unleash-tweet-10898786.php",
    "Visual": "http://ww4.hdnux.com/photos/56/70/27/12289523/3/1024x1024.jpg"
  },
  {
    "Day": 12,
    "Date": "Jan. 31",
    "ContentType": "trump today",
    "Topic": "Trump Today, Tech, Security",
    "NewsEvent": "Cybersecurity order signing",
    "Headline": "Trump cybersecurity order announcement canceled",
    "Link": "http://www.sfchronicle.com/business/article/Trump-update-Trump-expected-to-overhaul-10897499.php",
    "Visual": "http://ww2.hdnux.com/photos/56/67/41/12286041/3/920x1240.jpg"
  },
  {
    "Day": 12,
    "Date": "Jan. 31",
    "ContentType": "trump today",
    "Topic": "Trump Today, Cabinet",
    "NewsEvent": "Attorney general nomination",
    "Headline": "Feinstein to vote no on Sessions nomination",
    "Link": "http://www.sfchronicle.com/bayarea/article/Trump-update-Feinstein-to-vote-no-on-Sessions-10896827.php",
    "Visual": "http://ww4.hdnux.com/photos/56/67/14/12284703/5/920x920.jpg"
  },
  {
    "Day": 12,
    "Date": "Jan. 31",
    "ContentType": "trump today",
    "Topic": "Trump Today, Supreme Court",
    "NewsEvent": "Supreme Court pick, Neil Gorsuch",
    "Headline": "President jabs Pelosi, Schumer for mic snafu",
    "Link": "http://www.sfchronicle.com/news/article/Trump-update-President-jabs-Pelosi-Schumer-for-10896775.php",
    "Visual": "http://ww1.hdnux.com/photos/56/67/12/12284548/7/920x920.jpg"
  },
  {
    "Day": 12,
    "Date": "Jan. 31",
    "ContentType": "column",
    "Topic": "Trump Today, Democrats, Protests, Immigration",
    "NewsEvent": "Democrats' resistance to travel restrictions",
    "Headline": "Despite bold rhetoric, Dems, tech leaders collaborate with Trump",
    "Link": "http://www.sfchronicle.com/news/article/Despite-bold-rhetoric-Dems-tech-leaders-10895185.php"
  },
  {
    "Day": 12,
    "Date": "Jan. 31",
    "Key Event?": "Yes",
    "ContentType": "article",
    "Topic": "Supreme Court",
    "NewsEvent": "Supreme Court pick, Neil Gorsuch",
    "Headline": "Trump picks appeals court Judge Neil Gorsuch for Supreme Court",
    "Link": "http://www.sfchronicle.com/nation/article/Trump-picks-appeal-court-Judge-Neil-Gorsuch-for-10898443.php"
  },
  {
    "Day": 11,
    "Date": "Jan. 30",
    "ContentType": "article",
    "Topic": "Executive order, Immigration",
    "NewsEvent": "Immigration restrictions",
    "Headline": "Survival of Trump's refugee ban depends on how courts see it",
    "Link": "http://www.sfchronicle.com/nation/article/Survival-of-Trump-s-refugee-ban-depends-on-how-10895457.php"
  },
  {
    "Day": 11,
    "Date": "Jan. 30",
    "ContentType": "article",
    "Topic": "Trump supporters, Immigration",
    "NewsEvent": "Trump supporters' views",
    "Headline": "Liberals may hate Trump's first 10 days, but GOP base loves it",
    "Link": "http://www.sfchronicle.com/politics/article/Liberals-may-hate-Trump-s-first-10-days-but-10895770.php"
  },
  {
    "Day": 11,
    "Date": "Jan. 30",
    "ContentType": "article",
    "Topic": "Executive Order, Trump soundoffs",
    "NewsEvent": "Firing of acting attorney general ",
    "Headline": "Trump fires Justice Dept. head over executive order defiance",
    "Link": "http://www.sfchronicle.com/news/politics/article/Trump-faces-blowback-from-Cabinet-diplomats-for-10895134.php",
    "Visual": "http://ww2.hdnux.com/photos/56/66/45/12282217/3/920x920.jpg"
  },
  {
    "Day": 11,
    "Date": "Jan. 30",
    "Topic": "Business, Tech",
    "Headline": "White House’s shift frays Silicon Valley-Washington connections",
    "Link": "http://www.sfchronicle.com/business/article/White-House-s-shift-frays-Silicon-10892917.php"
  },
  {
    "Day": 11,
    "Date": "Jan. 30",
    "ContentType": "article",
    "Topic": "Travel ban, Immigration, Executive order",
    "NewsEvent": "Democrats' resistance to travel restrictions",
    "Headline": "Bay Area Dems' bids to stop Trump travel ban blocked in Congress",
    "Link": "http://www.sfchronicle.com/politics/article/Bay-Area-Dems-bids-to-stop-Trump-travel-ban-10895479.php"
  },
  {
    "Day": 10,
    "Date": "Jan. 29",
    "ContentType": "article",
    "Topic": "Executive order, Immigration",
    "NewsEvent": "Immigration restrictions",
    "Headline": "How tech companies responded to Trump's immigration ban",
    "Link": "http://www.sfchronicle.com/business/article/How-tech-companies-responded-to-Trump-s-10892794.php"
  },
  {
    "Day": 10,
    "Date": "Jan. 29",
    "ContentType": "online-only",
    "Topic": "Executive order, Immigration",
    "NewsEvent": "Immigration restrictions",
    "Headline": "Tech leaders, workers condemn Trump’s immigration ban",
    "Link": "http://www.sfchronicle.com/business/article/Tech-leaders-workers-condemn-Trump-s-10892365.php"
  },
  {
    "Day": 10,
    "Date": "Jan. 29",
    "ContentType": "column",
    "Topic": "Trump supporters ",
    "NewsEvent": "Arts world's approach to Trump",
    "Headline": "A terrifying vision of our Trump future at Sundance festival",
    "Link": "http://www.sfchronicle.com/news/article/A-terrifying-vision-of-our-Trump-future-at-10890665.php"
  },
  {
    "Day": 10,
    "Date": "Jan. 29",
    "Key Event?": "Yes",
    "ContentType": "article",
    "Topic": "Travel ban, Trade, Immigration",
    "NewsEvent": "Trump's implementation of promises",
    "Headline": "Trump's executive orders promise a lot, but can they deliver?",
    "Link": "http://www.sfchronicle.com/politics/article/Trump-s-executive-actions-promise-a-lot-but-10891688.php"
  },
  {
    "Day": 10,
    "Date": "Jan. 29",
    "ContentType": "article",
    "Topic": "Travel ban, Protests",
    "NewsEvent": "Protests over immigration restrictions",
    "Headline": "More than 1,000 protesters rally at SFO for immigration ban",
    "Link": "http://www.sfchronicle.com/news/article/Protesters-rally-at-SFO-following-immigration-ban-10892334.php",
    "Visual": "http://ww2.hdnux.com/photos/56/65/05/12276041/7/920x920.jpg"
  },
  {
    "Day": 10,
    "Date": "Jan. 29",
    "Key Event?": "Yes",
    "ContentType": "article",
    "Topic": "Executive order, Immigration",
    "NewsEvent": "Immigration restrictions",
    "Headline": "Anxious immigrant families caught in Trump order mostly relieved",
    "Link": "http://www.sfchronicle.com/bayarea/article/Immigrant-families-ensnared-by-Trump-order-10892568.php"
  },
  {
    "Day": 9,
    "Date": "Jan. 28",
    "ContentType": "column",
    "Topic": "Housing, Executive order",
    "NewsEvent": "EO on mortgage insurance",
    "Headline": "How the Trump and Ryan tax plans could impact homeownership",
    "Link": "http://www.sfchronicle.com/business/networth/article/How-the-Trump-and-Ryan-tax-plans-could-impact-10890200.php"
  },
  {
    "Day": 9,
    "Date": "Jan. 28",
    "ContentType": "column",
    "Topic": "Immigration, Executive order",
    "NewsEvent": "Trump's executive order on sanctuary cities",
    "Headline": "SF could be at top of Trump's enemies list",
    "Link": "http://www.sfchronicle.com/bayarea/williesworld/article/SF-could-be-at-the-top-of-Trump-s-enemies-list-10890714.php"
  },
  {
    "Day": 9,
    "Date": "Jan. 28",
    "Key Event?": "Yes",
    "ContentType": "article",
    "Topic": "Travel ban, Executive order",
    "NewsEvent": "Immigration restrictions",
    "Headline": "Bay Area fear over immigration ban turns to hope as judge lifts order ",
    "Link": "http://www.sfchronicle.com/bayarea/article/Confusion-heartbreak-over-Trump-order-on-10891257.php",
    "Visual": "http://ww4.hdnux.com/photos/56/63/45/12269915/3/920x920.jpg"
  },
  {
    "Day": 8,
    "Date": "Jan. 27",
    "ContentType": "article",
    "Topic": "Trump soundoffs, Election, Voter fraud",
    "NewsEvent": "Trump's accusations of illegal voting",
    "Headline": "State election officials reject Trump's claim of illegal voting",
    "Link": "http://www.sfchronicle.com/politics/article/State-election-officials-reject-Trump-s-claim-10890706.php"
  },
  {
    "Day": 8,
    "Date": "Jan. 27",
    "ContentType": "article",
    "Topic": "Immigration, Executive order",
    "NewsEvent": "Trump's stance toward Dreamers",
    "Headline": "Trump's unexpected delay on Dreamers baffles foes and supporters",
    "Link": "http://www.sfchronicle.com/nation/article/Trump-s-unexpected-delay-on-Dreamers-baffles-10889967.php"
  },
  {
    "Day": 8,
    "Date": "Jan. 27",
    "ContentType": "article",
    "Topic": "Executive order, Immigration",
    "NewsEvent": "SF Catholic Church reaction to immigration restrictions",
    "Headline": "SF archbishop on Trump: Church will aid undocumented immigrants",
    "Link": "http://www.sfchronicle.com/bayarea/article/SF-archbishop-troubled-by-Trump-s-10890368.php"
  },
  {
    "Day": 7,
    "Date": "Jan. 26",
    "ContentType": "column",
    "Topic": "Protests, Progressives",
    "NewsEvent": "Anti-Trump protests",
    "Headline": "After the protests, marching toward a real movement",
    "Link": "http://www.sfchronicle.com/politics/article/After-the-protests-marching-toward-a-real-10884526.php"
  },
  {
    "Day": 7,
    "Date": "Jan. 26",
    "ContentType": "article",
    "Topic": "Travel ban, Executive order, Immigration",
    "NewsEvent": "Immigration restrictions",
    "Headline": "Immigrants from Muslim nations fear what Trump changes will bring",
    "Link": "http://www.sfchronicle.com/politics/article/Immigrants-from-Muslim-nations-fear-what-Trump-10887478.php"
  },
  {
    "Day": 6,
    "Date": "Jan. 25",
    "Key Event?": "Yes",
    "ContentType": "article",
    "Topic": "Immigration, Sanctuary laws, Executive order",
    "NewsEvent": "Trump's executive order on sanctuary cities",
    "Headline": "SF Mayor Lee stands up to Trump, says city remains a sanctuary",
    "Link": "http://www.sfchronicle.com/bayarea/article/SF-Mayor-Lee-stands-up-to-Trump-says-city-10883956.php"
  },
  {
    "Day": 6,
    "Date": "Jan. 25",
    "Key Event?": "Yes",
    "ContentType": "article",
    "Topic": "Immigration, Wall, Executive order",
    "NewsEvent": "Wall executive order ",
    "Headline": "Trump moves to 'build that wall'",
    "Link": "http://www.sfchronicle.com/news/politics/article/Trump-to-move-on-border-security-immigration-10881395.php",
    "Visual": "http://ww4.hdnux.com/photos/56/54/55/12241731/7/920x920.jpg",
    "Other links": "https://www.whitehouse.gov/the-press-office/2017/01/25/executive-order-border-security-and-immigration-enforcement-improvements"
  },
  {
    "Day": 6,
    "Date": "Jan. 25",
    "ContentType": "column",
    "Topic": "Trump soundoffs",
    "NewsEvent": "Trump tweets",
    "Headline": "Trump could let companies get even sassier on Twitter",
    "Link": "http://www.sfchronicle.com/business/article/Trump-could-let-companies-get-even-sassier-on-10881360.php",
    "Visual": "http://ww4.hdnux.com/photos/56/54/55/12241731/7/920x920.jpg",
    "Other links": "https://www.whitehouse.gov/the-press-office/2017/01/25/executive-order-border-security-and-immigration-enforcement-improvements"
  },
  {
    "Day": 5,
    "Date": "Jan. 24",
    "ContentType": "column",
    "Topic": "Housing, Executive order",
    "NewsEvent": "EO on mortgage insurance",
    "Headline": "Trump’s swift mortgage move angers real estate industry",
    "Link": "http://www.sfchronicle.com/business/networth/article/Trump-s-swift-mortgage-move-angers-real-estate-10878383.php"
  },
  {
    "Day": 5,
    "Date": "Jan. 24",
    "Key Event?": "Yes",
    "ContentType": "article",
    "Topic": "Environment, California",
    "NewsEvent": "California resistance to Trump, California environmental policy",
    "Headline": "California set to fight Washington over environmental protections",
    "Link": "http://www.sfchronicle.com/science/article/California-set-to-fight-Washington-over-10881197.php"
  },
  {
    "Day": 5,
    "Date": "Jan. 24",
    "ContentType": "article",
    "Topic": "California",
    "NewsEvent": "California resistance to Trump",
    "Headline": "State of State speech: Jerry Brown takes on Trump",
    "Link": "http://www.sfchronicle.com/politics/article/State-of-State-speech-Jerry-Brown-takes-on-Trump-10880342.php"
  },
  {
    "Day": 5,
    "Date": "Jan. 24",
    "ContentType": "article",
    "Topic": "Trump soundoffs, Election, Voter fraud",
    "NewsEvent": "Election results",
    "Headline": "Trump repeats voter fraud falsehood to make himself look better",
    "Link": "http://www.sfchronicle.com/politics/article/Trump-repeats-voter-fraud-falsehood-to-make-10881470.php"
  },
  {
    "Day": 5,
    "Date": "Jan. 24",
    "ContentType": "article",
    "Topic": "Environment, Protests",
    "NewsEvent": "Trump orders to federal workers",
    "Headline": "Gag order, freeze put on EPA, other federal agencies",
    "Link": "http://www.sfchronicle.com/bayarea/article/Gag-order-freeze-put-on-EPA-other-federal-10881372.php"
  },
  {
    "Day": 4,
    "Date": "Jan. 23",
    "ContentType": "opinion",
    "Topic": "Trade, Executive order",
    "NewsEvent": "Trump abandons TPP ",
    "Headline": "Rest in peace, TPP",
    "Link": "http://www.sfchronicle.com/opinion/editorials/article/Rest-in-peace-Trans-Pacific-Partnership-10878311.php",
    "Visual": "http://ww4.hdnux.com/photos/56/54/65/12242255/5/920x1240.jpg"
  },
  {
    "Day": 3,
    "Date": "Jan. 22",
    "ContentType": "analysis",
    "Topic": "Homelessness, Federal aid",
    "NewsEvent": "Trump administration views on homeless aid",
    "Headline": "SF prepares to count its homeless, braces for cuts under Trump",
    "Link": "http://www.sfchronicle.com/bayarea/article/SF-prepares-to-count-its-homeless-braces-for-10874450.php"
  },
  {
    "Day": 2,
    "Date": "Jan. 21",
    "ContentType": "column",
    "Topic": "Inauguration",
    "NewsEvent": "Inauguration",
    "Headline": "In Trump's America, making friends isn't a priority",
    "Link": "http://www.sfchronicle.com/bayarea/williesworld/article/In-Trump-s-America-making-friends-isn-t-a-10873454.php"
  },
  {
    "Day": 2,
    "Date": "Jan. 21",
    "Key Event?": "Yes",
    "ContentType": "column",
    "Topic": "Protests",
    "NewsEvent": "women's rights",
    "Headline": "Women's march first step in lasting difference ",
    "Link": "http://www.sfchronicle.com/news/article/Women-s-March-is-just-the-1st-step-in-making-a-10875467.php",
    "Visual": "http://ww1.hdnux.com/photos/56/52/54/12233528/5/920x1240.jpg"
  },
  {
    "Day": 2,
    "Date": "Jan. 21",
    "Key Event?": "Yes",
    "ContentType": "news",
    "Topic": "Protests, Women",
    "NewsEvent": "women's rights",
    "Headline": "Huge crowds gather to demonstrate against Trump",
    "Link": "http://www.sfchronicle.com/bayarea/article/Crowds-gather-to-demonstrate-against-Trump-10873932.php",
    "Visual": "http://ww2.hdnux.com/photos/56/53/15/12235633/5/920x920.jpg"
  },
  {
    "Day": 2,
    "Date": "Jan. 21",
    "ContentType": "column",
    "Topic": "Inauguration, Trump soundoffs, Media",
    "NewsEvent": "Inauguration",
    "Headline": "A time for courage, from media as well as citizens",
    "Link": "http://www.sfchronicle.com/news/article/A-time-for-courage-from-media-as-well-as-citizens-10874231.php"
  },
  {
    "Day": 2,
    "Date": "Jan. 21",
    "Key Event?": "Yes",
    "ContentType": "news",
    "Topic": "Protests, Women",
    "NewsEvent": "women's rights",
    "Headline": "Huge crowd marches in Washington pledging to resist Trump",
    "Link": "http://www.sfchronicle.com/politics/article/Huge-crowd-marches-in-Washington-vowing-to-resist-10874384.php",
    "Visual": "http://ww2.hdnux.com/photos/56/52/25/12232053/5/1024x1024.jpg"
  },
  {
    "Day": 1,
    "Date": "Jan. 20",
    "ContentType": "analysis",
    "Topic": "Inauguration, Trump supporters",
    "NewsEvent": "Inauguration",
    "Headline": "In red Placer County, Republicans optimistic, confident in Trump",
    "Link": "http://www.sfchronicle.com/politics/article/In-red-Placer-County-Republicans-optimistic-10872927.php"
  },
  {
    "Day": 1,
    "Date": "Jan. 20",
    "ContentType": "analysis",
    "Topic": "Inauguration, Trump supporters",
    "NewsEvent": "Inauguration  ",
    "Headline": "Trump's victory is sweet for Californians who believed in him",
    "Link": "http://www.sfchronicle.com/politics/article/Trump-s-victory-is-sweet-for-Californians-who-10872971.php",
    "Visual": "http://ww2.hdnux.com/photos/56/51/51/12229205/3/920x920.jpg"
  },
  {
    "Day": 1,
    "Date": "Jan. 20",
    "ContentType": "news",
    "Topic": "Trump soundoffs, Inauguration, Protests",
    "NewsEvent": "Inauguration, protest",
    "Headline": "Thousands protest in SF and Oakland as Trump is sworn in",
    "Link": "http://www.sfchronicle.com/bayarea/article/Small-crowd-kicks-off-Inauguration-Day-protests-10871551.php",
    "Visual": "http://ww2.hdnux.com/photos/56/52/03/12230853/3/920x920.jpg"
  },
  {
    "Day": 1,
    "Date": "Jan. 20",
    "Key Event?": "Yes",
    "ContentType": "analysis",
    "Topic": "Trump soundoffs, Inauguration",
    "NewsEvent": "Inauguration, protest",
    "Headline": "With Trump inauguration, U.S. enters a great unknown",
    "Link": "http://www.sfchronicle.com/politics/article/With-Trump-inauguration-U-S-enters-great-unknown-10870262.php",
    "Visual": "http://ww4.hdnux.com/photos/56/47/60/12221459/5/920x1240.jpg"
  },
  {
    "Day": 1,
    "Date": "Jan. 20",
    "Key Event?": "Yes",
    "ContentType": "news",
    "Topic": "Trump soundoffs, Inauguration",
    "NewsEvent": "Inauguration",
    "Headline": "Trump takes office, promises an 'America first' approach",
    "Link": "http://www.sfchronicle.com/nation/article/Trump-takes-office-promises-an-America-10872851.php",
    "Visual": "http://ww3.hdnux.com/photos/56/51/50/12229122/5/920x1240.jpg"
  }
]